DbxPbiApiWrapper/BaseApiHelper.py
DbxPbiApiWrapper/BaseValueObjects.py
DbxPbiApiWrapper/DbxPbiWrapper.py
DbxPbiApiWrapper/__init__.py
DbxPbiApiWrapper-0.0.8.dist-info/LICENSE
DbxPbiApiWrapper-0.0.8.dist-info/METADATA
DbxPbiApiWrapper-0.0.8.dist-info/WHEEL
DbxPbiApiWrapper-0.0.8.dist-info/top_level.txt
DbxPbiApiWrapper-0.0.8.dist-info/RECORD
